LICENSE
MANIFEST.in
README.rst
setup.cfg
setup.py
tox.ini
cavy/__init__.py
cavy/testing.py
cavy.egg-info/PKG-INFO
cavy.egg-info/SOURCES.txt
cavy.egg-info/dependency_links.txt
cavy.egg-info/requires.txt
cavy.egg-info/top_level.txt
docs/conf.py
docs/custom.css
docs/index.rst
tests/__init__.py
tests/test_assertions_mixin.py
tests/test_env_mixin.py
tests/test_patching_mixin.py
tests/test_pep8_mixin.py