Metadata-Version: 2.1
Name: cavy
Version: 0.2.0
Summary: Library of unit testing helpers.
Home-page: https://cavy.readthedocs.io/
Author: Dave Shawley
Author-email: daveshawley@gmail.com
License: UNKNOWN
Project-URL: Builds, https://circleci.com/gh/dave-shawley/cavy
Project-URL: Documentation, https://cavy.readthedocs.io/
Project-URL: Source, https://github.com/dave-shawley/cavy/
Project-URL: Tracker, https://github.com/dave-shawley/cavy/issues/
Platform: UNKNOWN
Classifier: Intended Audience :: Developers
Classifier: License :: OSI Approved :: BSD License
Classifier: Development Status :: 4 - Beta
Classifier: Operating System :: OS Independent
Classifier: Programming Language :: Python
Classifier: Programming Language :: Python :: 3
Classifier: Programming Language :: Python :: 3.5
Classifier: Programming Language :: Python :: 3.6
Classifier: Programming Language :: Python :: 3.7
Classifier: Topic :: Software Development :: Libraries
Classifier: Topic :: Software Development :: Testing
Requires-Python: >=3
Provides-Extra: dev
